py_mysql/__init__.py
py_mysql/core.py
py_mysql/execute_queries.py
py_mysql/helpers.py
py_mysql/lib/__init__.py
py_mysql/lib/delete_null_row.py
py_mysql/lib/msg_abstract.py
py_mysql/lib/mysql_custom.py
py_mysql/lib/mysql/__init__.py
py_mysql/lib/mysql/connector/__init__.py
py_mysql/lib/mysql/connector/abstracts.py
py_mysql/lib/mysql/connector/authentication.py
py_mysql/lib/mysql/connector/catch23.py
py_mysql/lib/mysql/connector/charsets.py
py_mysql/lib/mysql/connector/connection.py
py_mysql/lib/mysql/connector/connection_cext.py
py_mysql/lib/mysql/connector/constants.py
py_mysql/lib/mysql/connector/conversion.py
py_mysql/lib/mysql/connector/cursor.py
py_mysql/lib/mysql/connector/cursor_cext.py
py_mysql/lib/mysql/connector/custom_types.py
py_mysql/lib/mysql/connector/dbapi.py
py_mysql/lib/mysql/connector/errorcode.py
py_mysql/lib/mysql/connector/errors.py
py_mysql/lib/mysql/connector/network.py
py_mysql/lib/mysql/connector/optionfiles.py
py_mysql/lib/mysql/connector/pooling.py
py_mysql/lib/mysql/connector/protocol.py
py_mysql/lib/mysql/connector/utils.py
py_mysql/lib/mysql/connector/version.py
py_mysql/lib/mysql/connector/django/__init__.py
py_mysql/lib/mysql/connector/django/base.py
py_mysql/lib/mysql/connector/django/client.py
py_mysql/lib/mysql/connector/django/compiler.py
py_mysql/lib/mysql/connector/django/creation.py
py_mysql/lib/mysql/connector/django/features.py
py_mysql/lib/mysql/connector/django/introspection.py
py_mysql/lib/mysql/connector/django/operations.py
py_mysql/lib/mysql/connector/django/schema.py
py_mysql/lib/mysql/connector/django/validation.py
py_mysql/lib/mysql/connector/fabric/__init__.py
py_mysql/lib/mysql/connector/fabric/balancing.py
py_mysql/lib/mysql/connector/fabric/caching.py
py_mysql/lib/mysql/connector/fabric/connection.py
py_mysql/lib/mysql/connector/locales/__init__.py
py_mysql/lib/mysql/connector/locales/eng/__init__.py
py_mysql/lib/mysql/connector/locales/eng/client_error.py
py_mysql-1.0.dist-info/DESCRIPTION.rst
py_mysql-1.0.dist-info/METADATA
py_mysql-1.0.dist-info/RECORD
py_mysql-1.0.dist-info/WHEEL
py_mysql-1.0.dist-info/entry_points.txt
py_mysql-1.0.dist-info/metadata.json
py_mysql-1.0.dist-info/top_level.txt
