Metadata-Version: 1.0
Name: py-mysql
Version: 1.0
Summary: Operating Mysql for Python.
Home-page: UNKNOWN
Author: Takeki Shikano
Author-email: shikano.takeki@nexon.co.jp
License: MIT
Platform: UNKNOWN
